setup.py
tubbs/__init__.py
tubbs/env.py
tubbs/logging.py
tubbs/main.py
tubbs/nvim_plugin.py
tubbs/state.py
tubbs.egg-info/PKG-INFO
tubbs.egg-info/SOURCES.txt
tubbs.egg-info/dependency_links.txt
tubbs.egg-info/requires.txt
tubbs.egg-info/top_level.txt
tubbs/formatter/__init__.py
tubbs/formatter/base.py
tubbs/formatter/crawler.py
tubbs/formatter/facade.py
tubbs/formatter/breaker/__init__.py
tubbs/formatter/breaker/breaks.py
tubbs/formatter/breaker/cond.py
tubbs/formatter/breaker/conds.py
tubbs/formatter/breaker/dsl.py
tubbs/formatter/breaker/info.py
tubbs/formatter/breaker/main.py
tubbs/formatter/breaker/rules.py
tubbs/formatter/breaker/state.py
tubbs/formatter/breaker/strict.py
tubbs/formatter/indenter/__init__.py
tubbs/formatter/indenter/cond.py
tubbs/formatter/indenter/conds.py
tubbs/formatter/indenter/dsl.py
tubbs/formatter/indenter/indent.py
tubbs/formatter/indenter/info.py
tubbs/formatter/indenter/main.py
tubbs/formatter/indenter/state.py
tubbs/formatter/scala/__init__.py
tubbs/formatter/scala/breaker.py
tubbs/formatter/scala/indenter.py
tubbs/formatter/scala/rewrite.py
tubbs/hints/__init__.py
tubbs/hints/base.py
tubbs/hints/scala.py
tubbs/parsers/__init__.py
tubbs/parsers/breaker_dsl.py
tubbs/parsers/indenter_dsl.py
tubbs/parsers/scala.py
tubbs/plugins/__init__.py
tubbs/plugins/core/__init__.py
tubbs/plugins/core/main.py
tubbs/plugins/core/message.py
tubbs/tatsu/__init__.py
tubbs/tatsu/ast.py
tubbs/tatsu/base.py
tubbs/tatsu/breaker_dsl.py
tubbs/tatsu/indenter_dsl.py
tubbs/tatsu/parser_ext.py
tubbs/tatsu/scala.py
tubbs/test/__init__.py
tubbs/test/spec.py
tubbs/util/__init__.py
tubbs/util/string.py