Metadata-Version: 1.0
Name: tubbs
Version: 0.6.5
Summary: ebnf-based text objects
Home-page: https://github.com/tek/tubbs
Author: Torsten Schmits
Author-email: torstenschmits@gmail.com
License: MIT
Platform: UNKNOWN
